{"hash":"53b98b29bad5caccfbd1c9ddfd6e5d93ee8c57f0","data":{"drink":{"name":"Dark 'n' Stormy","tags":[{"id":"iba-new-era","path":"/tagged/iba-new-era/"},{"id":"cocktail","path":"/tagged/cocktail/"},{"id":"all-day","path":"/tagged/all-day/"}],"ingredients":[{"item":{"id":"dark-rum","name":"Dark Rum","path":"/made-with/dark-rum/"},"amount":{"value":"6","unit":"cl"},"name":""},{"item":{"id":"ginger-beer","name":"Ginger Beer","path":"/made-with/ginger-beer/"},"amount":{"value":"10","unit":"cl"},"name":""}],"garnish":[]}},"context":{}}