{"hash":"53b98b29bad5caccfbd1c9ddfd6e5d93ee8c57f0","data":{"ingredient":{"name":"Sugar","belongsTo":{"edges":[{"node":{"id":"caipirinha","name":"Caipirinha","path":"/drinks/caipirinha/"}},{"node":{"id":"champagne-cocktail","name":"Champagne Cocktail","path":"/drinks/champagne-cocktail/"}},{"node":{"id":"lemon-drop","name":"Lemon Drop Martini","path":"/drinks/lemon-drop/"}},{"node":{"id":"mojito","name":"Mojito","path":"/drinks/mojito/"}},{"node":{"id":"old-fashioned","name":"Old Fashioned","path":"/drinks/old-fashioned/"}},{"node":{"id":"sazerac","name":"Sazerac","path":"/drinks/sazerac/"}}]}}},"context":{}}