{"hash":"3c1b39ecc6f3ea68f3e085355de365f9a54f8bf6","data":{"tag":{"id":"iba-new-era","belongsTo":{"edges":[{"node":{"id":"b-52","name":"B-52","path":"/drinks/b-52/"}},{"node":{"id":"barracuda","name":"Barracuda","path":"/drinks/barracuda/"}},{"node":{"id":"bramble","name":"Bramble","path":"/drinks/bramble/"}},{"node":{"id":"dark-n-stormy","name":"Dark 'n' Stormy","path":"/drinks/dark-n-stormy/"}},{"node":{"id":"dirty-martini","name":"Dirty Martini","path":"/drinks/dirty-martini/"}},{"node":{"id":"espresso-martini","name":"Espresso Martini","path":"/drinks/espresso-martini/"}},{"node":{"id":"french-martini","name":"French Martini","path":"/drinks/french-martini/"}},{"node":{"id":"kamikaze","name":"Kamikaze","path":"/drinks/kamikaze/"}},{"node":{"id":"lemon-drop","name":"Lemon Drop Martini","path":"/drinks/lemon-drop/"}},{"node":{"id":"pisco-sour","name":"Bacardi","path":"/drinks/pisco-sour/"}},{"node":{"id":"russian-spring-punch","name":"Russian Spring Punch","path":"/drinks/russian-spring-punch/"}},{"node":{"id":"spritz-veneziano","name":"Spritz Veneziano","path":"/drinks/spritz-veneziano/"}},{"node":{"id":"tommys-margarita","name":"Tommy's Margarita","path":"/drinks/tommys-margarita/"}},{"node":{"id":"vesper","name":"Vesper","path":"/drinks/vesper/"}},{"node":{"id":"yellow-bird","name":"Yellow Bird","path":"/drinks/yellow-bird/"}}]}}},"context":{}}